cage_data/__init__.py
cage_data/brMiscFxns.py
cage_data/brpylib.py
cage_data/cage_data.py
cage_data/load_intan_rhd_format.py
cage_data/intanutil/__init__.py
cage_data/intanutil/data_to_result.py
cage_data/intanutil/get_bytes_per_data_block.py
cage_data/intanutil/notch_filter.py
cage_data/intanutil/qstring.py
cage_data/intanutil/read_header.py
cage_data/intanutil/read_one_data_block.py
cage_data-1.2.1.dist-info/LICENSE
cage_data-1.2.1.dist-info/METADATA
cage_data-1.2.1.dist-info/WHEEL
cage_data-1.2.1.dist-info/top_level.txt
cage_data-1.2.1.dist-info/RECORD
