Metadata-Version: 2.1
Name: cage-data
Version: 1.2.1
Summary: Loading cage_data structure
Home-page: https://github.com/xuanma/cage_data
Author: Xuan Ma
Author-email: xuan.ma1@northwestern.edu
License: MIT Licence
Keywords: cage,limbLab,data loading
Platform: any
Requires-Dist: scipy
Requires-Dist: h5py
